mainpy/__init__.py
mainpy/py.typed
mainpy-1.5.0.dist-info/licenses/LICENSE
mainpy-1.5.0.dist-info/WHEEL
mainpy-1.5.0.dist-info/METADATA
mainpy-1.5.0.dist-info/RECORD
