Metadata-Version: 2.4
Name: mainpy
Version: 1.5.0
Summary: Simplify your project entrypoint with @main
Author: Joren Hammudoglu
Author-email: Joren Hammudoglu <jhammudoglu@gmail.com>
License-Expression: MIT
License-File: LICENSE
Classifier: Development Status :: 5 - Production/Stable
Classifier: Operating System :: OS Independent
Classifier: Programming Language :: Python :: 3.10
Classifier: Programming Language :: Python :: 3.11
Classifier: Programming Language :: Python :: 3.12
Classifier: Programming Language :: Python :: 3.13
Classifier: Programming Language :: Python :: 3.14
Classifier: Typing :: Typed
Requires-Dist: uvloop>=0.15.2 ; sys_platform != 'win32' and extra == 'uvloop'
Requires-Python: >=3.10
Project-URL: Changelog, https://github.com/jorenham/mainpy/releases
Project-URL: Documentation, https://github.com/jorenham/mainpy?tab=readme-ov-file#mainpy
Project-URL: Funding, https://github.com/sponsors/jorenham
Project-URL: Issues, https://github.com/jorenham/mainpy/issues
Project-URL: Repository, https://github.com/jorenham/mainpy
Provides-Extra: uvloop
